zenguard_benchmarks/__init__.py
zenguard_benchmarks/zenguard_prompt_attacks_benchmark.py
zenguard_benchmarks-0.1.5.dist-info/LICENSE
zenguard_benchmarks-0.1.5.dist-info/METADATA
zenguard_benchmarks-0.1.5.dist-info/WHEEL
zenguard_benchmarks-0.1.5.dist-info/RECORD
