Metadata-Version: 2.1
Name: zenguard-benchmarks
Version: 0.1.5
Summary: Test ZenGuard AI against different datasets and benchmarks.
License: MIT
Author: Baur Krykpayev
Author-email: baur@zenguard.ai
Requires-Python: >=3.9,<4.0
Classifier: License :: OSI Approved :: MIT License
Classifier: Programming Language :: Python :: 3
Classifier: Programming Language :: Python :: 3.9
Classifier: Programming Language :: Python :: 3.10
Classifier: Programming Language :: Python :: 3.11
Classifier: Programming Language :: Python :: 3.12
Requires-Dist: datasets (>=3.0.1,<4.0.0)
Requires-Dist: httpx (>=0.27.2,<0.28.0)
Requires-Dist: matplotlib (>=3.9.2,<4.0.0)
Requires-Dist: pandas (>=2.2.3,<3.0.0)
Requires-Dist: tqdm (>=4.66.5,<5.0.0)
